{
  "uid": "akina_nakamori23unofficial",
  "date": "2014-01-29",
  "genres": [],
  "review_done": false,
  "name": "ドラマティック・エアポート -Akina Travel Selection-",
  "artist": ["中森明菜"],
  "year": 2014,
  "list": [
    {
      "list": [
        [
          "",
          "北ウイング",
          "サザン・ウインド",
          "Bon Voyage",
          "100℃バカンス",
          "SAND BEIGE -砂漠へ-",
          "ジプシー・クイーン",
          "最後のカルメン",
          "ミ・アモーレ [Meu amor é…]",
          "トワイライト -夕暮れ便り-",
          "",
          "感傷紀行",
          "モナムール（グラスに半分の黄昏）",
          "Blue On Pink",
          "目を閉じて小旅行",
          "ヨコハマA・KU・MA",
          "メルヘン・ロケーション",
          "STAR PILOT",
          "ドラマティック・エアポート -北ウイングPart II-"
        ]
      ]
    }
  ],
  "rate": 81,
  "comment": "「旅」をテーマに選曲された非公認ベスト盤。アップテンポな曲から切ない曲まで幅広くあり、飽きさせることはない。シングルではなく、アルバム曲がメインになっているのもいいだろう。80年代の曲しか収録されていないが、個人的には12曲目が選ばれているのは素晴らしいと思う。14曲目は初期の超名曲だが、この曲を聴いても旅を感じることができるだろうか？",
  "recommend": ["SAND BEIGE", "ジプシー・クイーン", "Blue On Pink", "目を閉じて小旅行", "ヨコハマA・KU・MA"],
  "description": "非公認ベストアルバム",
  "type": "album",
  "img": ["akina23u.jpg"]
}
