{
  "artists": {
    "blind_guardian": {
      "name": "Blind Guardian",
      "ruby": "ブラインド・ガーディアン",
      "uid": "blind_guardian"
    },
    "black_sabbath": {
      "name": "Black Sabbath",
      "ruby": "ブラック・サバス",
      "uid": "black_sabbath"
    },
    "seiko": {
      "name": "松田聖子",
      "ruby": "まつだせいこ",
      "uid": "seiko"
    },
    "lumiere": {
      "name": "LUMIERE",
      "ruby": "ルミエール",
      "uid": "lumiere"
    },
    "veronica": {
      "name": "Veronica",
      "ruby": "ヴェロニカ",
      "uid": "veronica"
    },
    "nsfw": {
      "name": "Not Sale For Work",
      "ruby": "ノット・セール・フォー・ワーク",
      "uid": "nsfw"
    },
    "kagaribi": {
      "name": "篝火",
      "ruby": "かがりび",
      "uid": "kagaribi"
    },
    "die_fledermaus": {
      "name": "Die Fledermaus",
      "ruby": "フレーダーマウス",
      "uid": "die_fledermaus"
    },
    "jet_rat_fury": {
      "name": "JET RAT FURY",
      "ruby": "ジェット・ラット・フュリー",
      "uid": "jet_rat_fury"
    },
    "brave_child": {
      "name": "Brave Child",
      "ruby": "ブレイヴ・チャイルド",
      "uid": "brave_child"
    },
    "starish": {
      "name": "ST☆RISH",
      "ruby": "スターリッシュ",
      "uid": "starish"
    },
    "qn": {
      "name": "QUARTET NIGHT",
      "ruby": "カルテット・ナイト",
      "uid": "qn"
    },
    "heavens": {
      "name": "HE☆VENS",
      "ruby": "ヘヴンズ",
      "uid": "heavens"
    },
    "otoya": {
      "name": "一十木音也",
      "ruby": "いっときおとや",
      "uid": "otoya"
    },
    "masato": {
      "name": "聖川真斗",
      "ruby": "ひじりかわまさと",
      "uid": "masato"
    },
    "natsuki": {
      "name": "四ノ宮那月",
      "ruby": "しのみやなつき",
      "uid": "natsuki"
    },
    "ren": {
      "name": "神宮寺レン",
      "ruby": "じんぐうじれん",
      "uid": "ren"
    },
    "tokiya": {
      "name": "一ノ瀬トキヤ",
      "ruby": "いちのせときや",
      "uid": "tokiya"
    },
    "sho": {
      "name": "来栖翔",
      "ruby": "くるすしょう",
      "uid": "sho"
    },
    "hayato": {
      "name": "HAYATO",
      "ruby": "ハヤト",
      "uid": "hayato"
    },
    "reiji": {
      "name": "寿嶺二",
      "ruby": "ことぶきれいじ",
      "uid": "reiji"
    },
    "rammaru": {
      "name": "黒崎蘭丸"
    }
  }
}
