{"uid": "seiko_matsuda39", "date": "2005-12-07", "genres": [], "review_done": false, "name": "Under the beautiful stars", "artist": ["松田聖子"], "year": 2005, "list": [{"list": [["", "クリスマスの願い", "友達から恋人までの距離", "The time went by", "青春の日々", "", "あなたの翼", "思い出にできなくて [Album Version]", "戻れないあの日", "Under the beautiful stars"]]}], "rate": 83, "comment": "8年ぶりにリリースされたクリスマス向けのバラード・アルバム。1曲目は非常にレヴェルの高いメロディが支配する曲で、幻想的な雰囲気がクリスマスにピッタリ。2曲目はサビの質は高めだが、全体的にはそれほどパッとしない。3曲目は「しあわせな気持ち」のカップリング曲で、サビは透明感があっていい。4曲目はそれなりにいいメロディを使っているが、盛り上がりが弱め。5曲目はさらに良いメロディで埋まっているのだが、なんでか頭に残らない。6曲目は「I'll fall in love」のカップリングだが、正直サビ以外でのクオリティはない。7曲目は後にバラードベストに収録される曲で、落ち着いていて切なげな雰囲気がいい。8曲目はタイトルトラックだが、それにふさわしいだけの名曲だ。あまり印象に残らない曲があるのも確かだが、平均点は高め。さすがだ。", "recommend": ["クリスマスの願い", "The time went by", "思い出にできなくて", "戻れないあの日", "Under the beautiful stars"], "description": "39thアルバム", "type": "album", "img": ["seiko39.jpg"]}