{"uid": "alfee03", "date": "1980-05-21", "genres": [], "review_done": false, "name": "讃集詩 ", "artist": ["Alfee"], "year": 1980, "list": [{"list": [["", "やすらぎをもとめて", "Something Blue", "帰郷", "逆もどり浮気考", "明日なき暴走の果てに", "坂道", "", "落日の風", "ロンサム・シティ", "無言劇", "追想", "Musician"]]}], "rate": 95, "comment": "再デビュー後2作目にして、早くもフォーク路線の大傑作に仕上がった。前作よりも明るく軽快な雰囲気の曲が増えたのも特徴のひとつだが、やはり注目せざるを得ないのが高見沢のエレキギター解禁である。これまではフォーク・バンドとしてアコギのみを使っていたのだが、⑦の間奏でエレキギターを弾いている。おそらくこれが、アルフィーのロック化に繋がったことは言わずもがなである。前作はB面が物凄い高品質だったのだが、今作はA,B問わず名曲の集合体だ。だがやはりどちらかと言えば中盤以降のレヴェルが高いことが指摘できる。具体的には⑤以降だ。アルフィー初期のテーマソングともいうべき⑤に始まり、桜井の超絶ヴォーカルに涙腺が緩む本作一の名バラード⑥、ノリのいいテンポで進む⑦、高見沢ヴォーカル初期の名曲でありアルフィー長年のサブテーマでもある1969を歌った⑧、初期アルフィー問答無用の傑作シングル⑨、アルフィー史上最も暗いが歌詞が心を打つ⑩、そして初期の代表曲筆頭の⑪。名曲・代表曲が目白押しの非常に豪華な作品なのだ。ロック時代しか聴いたことないが、フォーク時代の曲にも興味があるという人は、まずこの作品から聴くことをお勧めする。", "recommend": ["全部　特に明日なき暴走の果てに", "坂道", "落日の風", "ロンサム・シティ", "無言劇", "Musician"], "description": "3rdアルバム", "type": "album", "img": ["alfee03.jpg"]}