{"uid": "alice_nine05", "date": "", "genres": [], "review_done": false, "name": "“9” ", "artist": ["Alice Nine"], "year": 2012, "list": [{"list": [["", "Heavenly Tale", "the Arc", "GALLOWS", "花霞", "BLUE FLAME", "ハロー、ワールド", "", "虹の雪", "リニア", "Apocalypse [It's not the end]", "Heart of Gold", "すべてへ"]]}], "rate": 94, "comment": "ヴィジュアル系ロックバンドの5作目。岡野ハジメとの共同作業によって培われたノウハウを活かし、アルバムの全像をしっかり見据えて制作できるようになったのだろう。また自分たちの表現したいことがきちんと表現できる力量が身についたのも大きい。全体的にソリッドでタイトな仕上がりとなっていて、出来る限り無駄が省かれている。本作でもオープニングはやはり壮大な曲。そして何より注目なのは、本作で初めてメロディック・スピード・メタルに挑戦している！しかも超名曲！これまでのメタリックな曲はあったが、ここまで振り切れたのは意外だった。引き続いて#3もメタリックな曲で、#2と合わせて聴くと怒涛の猛攻撃という印象だ。シングル#5もハードなギターパートもある爽快なロックだが、これまでにない大人びた雰囲気がある。ヘヴィネスとメロディが絶妙に絡んだ#9も会心の出来だ。しかしもちろんメロディックでメロウな曲もあり、#4や#7がそれにあたる。特に#7はVo.将が初めて作曲した曲であり、ポップで大衆性のある仕上がりだ。また語りが大部分を占めるという大胆な曲#6など、挑戦的な一面もある。そしてポジティヴで疾走感ある#10、バラード調～メロディック・ハードに展開するラストチューンの流れも完璧。緊張感や新鮮さでは前作のほうが上だが、より彼ららしい音であるのはこちらだ。", "recommend": ["全部　特にHeavenly Tale", "the Arc", "GALLOWS", "BLUE FLAME", "すべてへ"], "description": "Nine 5thアルバム", "type": "album", "img": ["alice905_b.jpg"]}